sys_ej/__init__.py
sys_ej-0.1.0.dist-info/METADATA
sys_ej-0.1.0.dist-info/WHEEL
sys_ej-0.1.0.dist-info/RECORD
