Metadata-Version: 2.1
Name: sys-ej
Version: 0.1.0
Summary: basic calculator
Author: ykgg
Requires-Python: >=3.10,<4.0
Classifier: Programming Language :: Python :: 3
Classifier: Programming Language :: Python :: 3.10
Classifier: Programming Language :: Python :: 3.11
